gitlabbot/__init__.py
gitlabbot/__version__.py
gitlabbot/setting.py
gitlabbot/cli/__init__.py
gitlabbot/cli/flux_diff.py
gitlabbot/note/__init__.py
gitlabbot/note/utils.py
gitlabbot-0.3.5.dist-info/METADATA
gitlabbot-0.3.5.dist-info/WHEEL
gitlabbot-0.3.5.dist-info/entry_points.txt
gitlabbot-0.3.5.dist-info/licenses/LICENSE
gitlabbot-0.3.5.dist-info/RECORD
