Metadata-Version: 2.4
Name: gitlabbot
Version: 0.3.5
Summary: Make comment on gitlab using `flux-local` diff outputs.
License-Expression: Apache-2.0
License-File: LICENSE
Classifier: Programming Language :: Python :: 3 :: Only
Classifier: Programming Language :: Python :: 3.12
Classifier: Programming Language :: Python :: 3.13
Requires-Python: >=3.12
Requires-Dist: flux-local>=7.2.1
Requires-Dist: loguru>=0.7.3
Requires-Dist: pydantic-cli>=9.1
Requires-Dist: pydantic-settings>=2.8.1
Requires-Dist: pydantic>=2.10.6
Requires-Dist: python-gitlab>=5.6
